LICENSE
MANIFEST.in
README.md
setup.cfg
setup.py
dfiibridge/__init__.py
dfiibridge/abstract_translator.py
dfiibridge/abstract_workspace.py
dfiibridge/callback_decorator.py
dfiibridge/functions.py
dfiibridge/hints.py
dfiibridge/logger.py
dfiibridge/objects.py
dfiibridge/sessions.py
dfiibridge/translator.py
dfiibridge/workspace.py
dfiibridge.egg-info/PKG-INFO
dfiibridge.egg-info/SOURCES.txt
dfiibridge.egg-info/dependency_links.txt
dfiibridge.egg-info/not-zip-safe
dfiibridge.egg-info/requires.txt
dfiibridge.egg-info/top_level.txt
dfiibridge_server/__init__.py
dfiibridge_server/dfiiBridgeClient.il
dfiibridge_server/dfiiBridgeServer.il
dfiibridge_server/dfiiBridgeUtils.il
dfiibridge_server/globals.py
dfiibridge_server/helpers.py
dfiibridge_server/session_maker.py
dfiibridge_server/virtuoso_client.py
dfiibridge_server/virtuoso_server.py
swig/include/Channel.hpp
swig/include/ChannelClient.hpp
swig/include/ChannelServer.hpp
swig/include/CoreSessionManager.hpp
swig/include/DfiiBridgeClient.hpp
swig/include/DfiiBridgeCore.hpp
swig/include/DfiiBridgeServer.hpp
swig/include/LoggingCallback.hpp
swig/include/RemoteCallback.hpp
swig/include/Session.hpp
swig/include/globals.hpp
swig/include/zmq.hpp
swig/include/nlohmann/json.hpp
swig/src/Channel.cpp
swig/src/ChannelClient.cpp
swig/src/ChannelServer.cpp
swig/src/CoreSessionManager.cpp
swig/src/DfiiBridge.i
swig/src/DfiiBridgeClient.cpp
swig/src/DfiiBridgeCore.cpp
swig/src/DfiiBridgeServer.cpp
swig/src/Session.cpp