Metadata-Version: 2.1
Name: dfiibridge
Version: 1.1.0
Summary: attr: dfiibridge_server.__description__
Home-page: https://gitlab.com/mosaic_group/mosaic_framework/dfiibridge
Author: attr: dfiibridge_server.__author__
Author-email: R-IFX-anagen@infineon.com
License: GPL3
Requires-Python: >=3.7
License-File: LICENSE
